LICENSE.txt
MANIFEST.in
README.md
setup.cfg
setup.py
goldman/__init__.py
goldman/api.py
goldman/config.py
goldman/exceptions.py
goldman/extensions.py
goldman/mimetypes.py
goldman/request.py
goldman/response.py
goldman/signals.py
goldman.egg-info/PKG-INFO
goldman.egg-info/SOURCES.txt
goldman.egg-info/dependency_links.txt
goldman.egg-info/requires.txt
goldman.egg-info/top_level.txt
goldman/deserializers/__init__.py
goldman/deserializers/base.py
goldman/deserializers/comma_sep.py
goldman/deserializers/form_data.py
goldman/deserializers/form_urlencoded.py
goldman/deserializers/json_7159.py
goldman/deserializers/jsonapi.py
goldman/middleware/__init__.py
goldman/middleware/basicauth/__init__.py
goldman/middleware/bearer_token/__init__.py
goldman/middleware/deserializer/__init__.py
goldman/middleware/http_specs/__init__.py
goldman/middleware/model_qps/__init__.py
goldman/middleware/rate_limit/__init__.py
goldman/middleware/security/__init__.py
goldman/middleware/serializer/__init__.py
goldman/middleware/threadlocal/__init__.py
goldman/models/__init__.py
goldman/models/base.py
goldman/models/default_schema.py
goldman/models/login.py
goldman/queryparams/__init__.py
goldman/queryparams/fields.py
goldman/queryparams/filter.py
goldman/queryparams/include.py
goldman/queryparams/page.py
goldman/queryparams/sort.py
goldman/resources/__init__.py
goldman/resources/base.py
goldman/resources/json_7159.py
goldman/resources/model.py
goldman/resources/models.py
goldman/resources/oauth_revoke.py
goldman/resources/oauth_ropc.py
goldman/resources/related.py
goldman/resources/s3_model.py
goldman/resources/s3_model_image.py
goldman/serializers/__init__.py
goldman/serializers/base.py
goldman/serializers/comma_sep.py
goldman/serializers/json_7159.py
goldman/serializers/jsonapi.py
goldman/serializers/jsonapi_error.py
goldman/stores/__init__.py
goldman/stores/base.py
goldman/stores/postgres/__init__.py
goldman/stores/postgres/connect.py
goldman/stores/postgres/store.py
goldman/types/__init__.py
goldman/types/datetime.py
goldman/types/latitude.py
goldman/types/longitude.py
goldman/types/phonenumber.py
goldman/types/resource.py
