Metadata-Version: 1.1
Name: goldman
Version: 0.1.9
Summary: An opinionated WSGI web framework
Home-page: https://github.com/sassoo/goldman
Author: Sassoo
Author-email: noreply@devnull.seriously
License: MIT
Download-URL: https://github.com/sassoo/goldman/tarball/0.1.9
Keywords: framework,http,jsonapi,rest,web,wsgi
Platform: UNKNOWN
Classifier: Intended Audience :: Developers
Classifier: Intended Audience :: System Administrators
Classifier: Topic :: Internet :: WWW/HTTP :: WSGI
Classifier: Topic :: Software Development :: Libraries :: Application Frameworks
Classifier: Programming Language :: Python
Classifier: Programming Language :: Python :: 2.7
